rfc/__init__.py
rfc/rfc.py
rfc_reader-1.0.dist-info/DESCRIPTION.rst
rfc_reader-1.0.dist-info/METADATA
rfc_reader-1.0.dist-info/RECORD
rfc_reader-1.0.dist-info/WHEEL
rfc_reader-1.0.dist-info/entry_points.txt
rfc_reader-1.0.dist-info/metadata.json
rfc_reader-1.0.dist-info/top_level.txt
