Metadata-Version: 2.0
Name: rfc-reader
Version: 1.0
Summary: Consult download and search through IETF RFC documents from your terminal
Home-page: https://github.com/monsieurh/rfc_reader
Author: monsieur_h
Author-email: ray.hubert@gmail.com
License: GPL3
Keywords: RFC rfc IETF rfc_reader rfc-reader
Platform: any
Classifier: Programming Language :: Python :: 2.7
Classifier: Programming Language :: Python :: 3.4
Classifier: Programming Language :: Python :: 3.5
Classifier: Development Status :: 4 - Beta
Classifier: Environment :: Console
Classifier: Intended Audience :: Developers
Classifier: Intended Audience :: Information Technology
Classifier: Intended Audience :: Legal Industry
Classifier: License :: OSI Approved :: GNU General Public License v3 (GPLv3)
Classifier: License :: Public Domain
Classifier: Natural Language :: English
Classifier: Operating System :: POSIX
Classifier: Operating System :: Unix
Classifier: Topic :: Internet
Classifier: Topic :: Software Development
Classifier: Topic :: Software Development :: Debuggers
